LICENSE
MANIFEST.in
README.md
setup.cfg
setup.py
cexbot/__init__.py
cexbot/__main__.py
cexbot/cex.py
cexbot/cexapi.py
cexbot/command_utils.py
cexbot/commands.py
cexbot/config.py
cexbot/db.py
cexbot/singleton.py
cexbot/tasks.py
cexbot/timer.py
cexbot/updater.py
cexbot.egg-info/PKG-INFO
cexbot.egg-info/SOURCES.txt
cexbot.egg-info/dependency_links.txt
cexbot.egg-info/entry_points.txt
cexbot.egg-info/requires.txt
cexbot.egg-info/top_level.txt