Metadata-Version: 1.0
Name: cexbot
Version: 0.0.10d1
Summary: cexbot
